{
  "advisor_summary": [
    {
      "detail": "SPY \u9ad8\u4e8e MA200\uff0c\u4f46\u4ecd\u9700\u6309\u4ed3\u4f4d\u4e0a\u9650\u548c\u4f30\u503c\u6781\u503c\u89c4\u5219\u4fee\u526a\u8fc7\u5ea6\u96c6\u4e2d\u3002",
      "rank": 1,
      "rule_ids": [
        "TREND_200DMA",
        "POSITION_CAP",
        "SECTOR_CAP"
      ],
      "severity": "medium",
      "title": "\u8d8b\u52bf\u4ecd\u652f\u6301\u6301\u6709\u98ce\u9669\u8d44\u4ea7"
    },
    {
      "detail": "HOLD CASH +29.81%\uff1araise or maintain cash buffer",
      "rank": 2,
      "rule_ids": [
        "CASH_BUFFER"
      ],
      "severity": "medium",
      "title": "\u5efa\u8bae\u63d0\u9ad8\u73b0\u91d1\u7f13\u51b2"
    },
    {
      "detail": "TRIM AAPL -6.55%\uff1aexceeds max single-name cap; over target weight; sector exceeds max cap",
      "rank": 3,
      "rule_ids": [
        "OVER_TARGET",
        "SECTOR_CAP",
        "SINGLE_CAP"
      ],
      "severity": "high",
      "title": "\u4f18\u5148\u4fee\u526a AAPL"
    },
    {
      "detail": "TRIM MSFT -5.45%\uff1aover target weight; sector exceeds max cap; trailing-stop triggered",
      "rank": 4,
      "rule_ids": [
        "OVER_TARGET",
        "SECTOR_CAP",
        "TRAILING_STOP"
      ],
      "severity": "high",
      "title": "\u4f18\u5148\u4fee\u526a MSFT"
    },
    {
      "detail": "TRIM AVGO -5.00%\uff1asector exceeds max cap; stop-loss triggered; trailing-stop triggered",
      "rank": 5,
      "rule_ids": [
        "SECTOR_CAP",
        "STOP_LOSS",
        "TRAILING_STOP"
      ],
      "severity": "high",
      "title": "\u4f18\u5148\u4fee\u526a AVGO"
    },
    {
      "detail": "TRIM NVDA -5.00%\uff1aover target weight; sector exceeds max cap",
      "rank": 6,
      "rule_ids": [
        "OVER_TARGET",
        "SECTOR_CAP"
      ],
      "severity": "medium",
      "title": "\u4f18\u5148\u4fee\u526a NVDA"
    }
  ],
  "benchmark_series": [
    {
      "date": "2025-07-09",
      "value": 617.2210083007812
    },
    {
      "date": "2025-07-10",
      "value": 618.9617919921875
    },
    {
      "date": "2025-07-11",
      "value": 616.7858276367188
    },
    {
      "date": "2025-07-14",
      "value": 617.9627685546875
    },
    {
      "date": "2025-07-15",
      "value": 615.3220825195312
    },
    {
      "date": "2025-07-16",
      "value": 617.3792724609375
    },
    {
      "date": "2025-07-17",
      "value": 621.1574096679688
    },
    {
      "date": "2025-07-18",
      "value": 620.7024536132812
    },
    {
      "date": "2025-07-21",
      "value": 621.87939453125
    },
    {
      "date": "2025-07-22",
      "value": 621.9683837890625
    },
    {
      "date": "2025-07-23",
      "value": 627.2598876953125
    },
    {
      "date": "2025-07-24",
      "value": 627.4674682617188
    },
    {
      "date": "2025-07-25",
      "value": 630.1181640625
    },
    {
      "date": "2025-07-28",
      "value": 629.9598388671875
    },
    {
      "date": "2025-07-29",
      "value": 628.29833984375
    },
    {
      "date": "2025-07-30",
      "value": 627.5070190429688
    },
    {
      "date": "2025-07-31",
      "value": 625.1531372070312
    },
    {
      "date": "2025-08-01",
      "value": 614.9066162109375
    },
    {
      "date": "2025-08-04",
      "value": 624.2530517578125
    },
    {
      "date": "2025-08-05",
      "value": 621.088134765625
    },
    {
      "date": "2025-08-06",
      "value": 625.845458984375
    },
    {
      "date": "2025-08-07",
      "value": 625.3212890625
    },
    {
      "date": "2025-08-08",
      "value": 630.1972045898438
    },
    {
      "date": "2025-08-11",
      "value": 628.9509887695312
    },
    {
      "date": "2025-08-12",
      "value": 635.6469116210938
    },
    {
      "date": "2025-08-13",
      "value": 637.82275390625
    },
    {
      "date": "2025-08-14",
      "value": 637.882080078125
    },
    {
      "date": "2025-08-15",
      "value": 636.3886108398438
    },
    {
      "date": "2025-08-18",
      "value": 636.2501220703125
    },
    {
      "date": "2025-08-19",
      "value": 632.7984008789062
    },
    {
      "date": "2025-08-20",
      "value": 631.1170043945312
    },
    {
      "date": "2025-08-21",
      "value": 628.5850830078125
    },
    {
      "date": "2025-08-22",
      "value": 638.2380981445312
    },
    {
      "date": "2025-08-25",
      "value": 635.4292602539062
    },
    {
      "date": "2025-08-26",
      "value": 638.0897827148438
    },
    {
      "date": "2025-08-27",
      "value": 639.543701171875
    },
    {
      "date": "2025-08-28",
      "value": 641.80859375
    },
    {
      "date": "2025-08-29",
      "value": 637.9810180664062
    },
    {
      "date": "2025-09-02",
      "value": 633.2533569335938
    },
    {
      "date": "2025-09-03",
      "value": 636.6853637695312
    },
    {
      "date": "2025-09-04",
      "value": 642.00634765625
    },
    {
      "date": "2025-09-05",
      "value": 640.1469116210938
    },
    {
      "date": "2025-09-08",
      "value": 641.7196044921875
    },
    {
      "date": "2025-09-09",
      "value": 643.2031860351562
    },
    {
      "date": "2025-09-10",
      "value": 645.0625
    },
    {
      "date": "2025-09-11",
      "value": 650.4231567382812
    },
    {
      "date": "2025-09-12",
      "value": 650.2054443359375
    },
    {
      "date": "2025-09-15",
      "value": 653.6671142578125
    },
    {
      "date": "2025-09-16",
      "value": 652.7671508789062
    },
    {
      "date": "2025-09-17",
      "value": 651.9561157226562
    },
    {
      "date": "2025-09-18",
      "value": 655.0023803710938
    },
    {
      "date": "2025-09-19",
      "value": 658.2465209960938
    },
    {
      "date": "2025-09-22",
      "value": 661.3607788085938
    },
    {
      "date": "2025-09-23",
      "value": 657.7606201171875
    },
    {
      "date": "2025-09-24",
      "value": 655.6678466796875
    },
    {
      "date": "2025-09-25",
      "value": 652.6429443359375
    },
    {
      "date": "2025-09-26",
      "value": 656.3820190429688
    },
    {
      "date": "2025-09-29",
      "value": 658.2266845703125
    },
    {
      "date": "2025-09-30",
      "value": 660.7061157226562
    },
    {
      "date": "2025-10-01",
      "value": 662.9574584960938
    },
    {
      "date": "2025-10-02",
      "value": 663.7210693359375
    },
    {
      "date": "2025-10-03",
      "value": 663.7112426757812
    },
    {
      "date": "2025-10-06",
      "value": 666.0914916992188
    },
    {
      "date": "2025-10-07",
      "value": 663.6219482421875
    },
    {
      "date": "2025-10-08",
      "value": 667.5791625976562
    },
    {
      "date": "2025-10-09",
      "value": 665.6452026367188
    },
    {
      "date": "2025-10-10",
      "value": 647.6542358398438
    },
    {
      "date": "2025-10-13",
      "value": 657.5919189453125
    },
    {
      "date": "2025-10-14",
      "value": 656.78857421875
    },
    {
      "date": "2025-10-15",
      "value": 659.7044067382812
    },
    {
      "date": "2025-10-16",
      "value": 655.2116088867188
    },
    {
      "date": "2025-10-17",
      "value": 658.9308471679688
    },
    {
      "date": "2025-10-20",
      "value": 665.7840576171875
    },
    {
      "date": "2025-10-21",
      "value": 665.7741088867188
    },
    {
      "date": "2025-10-22",
      "value": 662.3128051757812
    },
    {
      "date": "2025-10-23",
      "value": 666.2402954101562
    },
    {
      "date": "2025-10-24",
      "value": 671.6851806640625
    },
    {
      "date": "2025-10-27",
      "value": 679.6094970703125
    },
    {
      "date": "2025-10-28",
      "value": 681.41455078125
    },
    {
      "date": "2025-10-29",
      "value": 681.7418823242188
    },
    {
      "date": "2025-10-30",
      "value": 674.2440185546875
    },
    {
      "date": "2025-10-31",
      "value": 676.45556640625
    },
    {
      "date": "2025-11-03",
      "value": 677.7251586914062
    },
    {
      "date": "2025-11-04",
      "value": 669.6917114257812
    },
    {
      "date": "2025-11-05",
      "value": 672.012451171875
    },
    {
      "date": "2025-11-06",
      "value": 664.8021850585938
    },
    {
      "date": "2025-11-07",
      "value": 665.4567260742188
    },
    {
      "date": "2025-11-10",
      "value": 675.8406982421875
    },
    {
      "date": "2025-11-11",
      "value": 677.3878784179688
    },
    {
      "date": "2025-11-12",
      "value": 677.7648315429688
    },
    {
      "date": "2025-11-13",
      "value": 666.5180053710938
    },
    {
      "date": "2025-11-14",
      "value": 666.4088745117188
    },
    {
      "date": "2025-11-17",
      "value": 660.2003173828125
    },
    {
      "date": "2025-11-18",
      "value": 654.65625
    },
    {
      "date": "2025-11-19",
      "value": 657.185302734375
    },
    {
      "date": "2025-11-20",
      "value": 647.1683349609375
    },
    {
      "date": "2025-11-21",
      "value": 653.6149291992188
    },
    {
      "date": "2025-11-24",
      "value": 663.235107421875
    },
    {
      "date": "2025-11-25",
      "value": 669.4735107421875
    },
    {
      "date": "2025-11-26",
      "value": 674.09521484375
    },
    {
      "date": "2025-11-28",
      "value": 677.7747192382812
    },
    {
      "date": "2025-12-01",
      "value": 674.6802978515625
    },
    {
      "date": "2025-12-02",
      "value": 675.9300537109375
    },
    {
      "date": "2025-12-03",
      "value": 678.2706298828125
    },
    {
      "date": "2025-12-04",
      "value": 678.7664794921875
    },
    {
      "date": "2025-12-05",
      "value": 680.0557861328125
    },
    {
      "date": "2025-12-08",
      "value": 678.0127563476562
    },
    {
      "date": "2025-12-09",
      "value": 677.4275512695312
    },
    {
      "date": "2025-12-10",
      "value": 681.92041015625
    },
    {
      "date": "2025-12-11",
      "value": 683.5072021484375
    },
    {
      "date": "2025-12-12",
      "value": 676.1581420898438
    },
    {
      "date": "2025-12-15",
      "value": 675.1365356445312
    },
    {
      "date": "2025-12-16",
      "value": 673.2918701171875
    },
    {
      "date": "2025-12-17",
      "value": 665.8832397460938
    },
    {
      "date": "2025-12-18",
      "value": 670.9114990234375
    },
    {
      "date": "2025-12-19",
      "value": 676.9923095703125
    },
    {
      "date": "2025-12-22",
      "value": 681.2098999023438
    },
    {
      "date": "2025-12-23",
      "value": 684.3233032226562
    },
    {
      "date": "2025-12-24",
      "value": 686.7305297851562
    },
    {
      "date": "2025-12-26",
      "value": 686.660888671875
    },
    {
      "date": "2025-12-29",
      "value": 684.2138671875
    },
    {
      "date": "2025-12-30",
      "value": 683.3783569335938
    },
    {
      "date": "2025-12-31",
      "value": 678.3152465820312
    },
    {
      "date": "2026-01-02",
      "value": 679.55859375
    },
    {
      "date": "2026-01-05",
      "value": 684.0845336914062
    },
    {
      "date": "2026-01-06",
      "value": 688.1529541015625
    },
    {
      "date": "2026-01-07",
      "value": 685.9347534179688
    },
    {
      "date": "2026-01-08",
      "value": 685.8651123046875
    },
    {
      "date": "2026-01-09",
      "value": 690.4010009765625
    },
    {
      "date": "2026-01-12",
      "value": 691.4852294921875
    },
    {
      "date": "2026-01-13",
      "value": 690.1026000976562
    },
    {
      "date": "2026-01-14",
      "value": 686.7106323242188
    },
    {
      "date": "2026-01-15",
      "value": 688.5806884765625
    },
    {
      "date": "2026-01-16",
      "value": 688.0037231445312
    },
    {
      "date": "2026-01-20",
      "value": 673.9981689453125
    },
    {
      "date": "2026-01-21",
      "value": 681.77685546875
    },
    {
      "date": "2026-01-22",
      "value": 685.3379516601562
    },
    {
      "date": "2026-01-23",
      "value": 685.5865478515625
    },
    {
      "date": "2026-01-26",
      "value": 689.0680541992188
    },
    {
      "date": "2026-01-27",
      "value": 691.8134765625
    },
    {
      "date": "2026-01-28",
      "value": 691.7438354492188
    },
    {
      "date": "2026-01-29",
      "value": 690.3711547851562
    },
    {
      "date": "2026-01-30",
      "value": 688.3120727539062
    },
    {
      "date": "2026-02-02",
      "value": 691.7339477539062
    },
    {
      "date": "2026-02-03",
      "value": 685.885009765625
    },
    {
      "date": "2026-02-04",
      "value": 682.5626831054688
    },
    {
      "date": "2026-02-05",
      "value": 674.0379638671875
    },
    {
      "date": "2026-02-06",
      "value": 686.96923828125
    },
    {
      "date": "2026-02-09",
      "value": 690.2816772460938
    },
    {
      "date": "2026-02-10",
      "value": 688.4613037109375
    },
    {
      "date": "2026-02-11",
      "value": 688.3021850585938
    },
    {
      "date": "2026-02-12",
      "value": 677.668701171875
    },
    {
      "date": "2026-02-13",
      "value": 678.1461181640625
    },
    {
      "date": "2026-02-17",
      "value": 679.2402954101562
    },
    {
      "date": "2026-02-18",
      "value": 682.662109375
    },
    {
      "date": "2026-02-19",
      "value": 680.8616333007812
    },
    {
      "date": "2026-02-20",
      "value": 685.7855834960938
    },
    {
      "date": "2026-02-23",
      "value": 678.7827758789062
    },
    {
      "date": "2026-02-24",
      "value": 683.7164916992188
    },
    {
      "date": "2026-02-25",
      "value": 689.4859008789062
    },
    {
      "date": "2026-02-26",
      "value": 685.6561889648438
    },
    {
      "date": "2026-02-27",
      "value": 682.3637084960938
    },
    {
      "date": "2026-03-02",
      "value": 682.751708984375
    },
    {
      "date": "2026-03-03",
      "value": 676.7337036132812
    },
    {
      "date": "2026-03-04",
      "value": 681.5082397460938
    },
    {
      "date": "2026-03-05",
      "value": 677.70849609375
    },
    {
      "date": "2026-03-06",
      "value": 668.82568359375
    },
    {
      "date": "2026-03-09",
      "value": 674.6845703125
    },
    {
      "date": "2026-03-10",
      "value": 673.6002807617188
    },
    {
      "date": "2026-03-11",
      "value": 672.7548217773438
    },
    {
      "date": "2026-03-12",
      "value": 662.5390625
    },
    {
      "date": "2026-03-13",
      "value": 658.7890014648438
    },
    {
      "date": "2026-03-16",
      "value": 665.493408203125
    },
    {
      "date": "2026-03-17",
      "value": 667.2440185546875
    },
    {
      "date": "2026-03-18",
      "value": 657.9335327148438
    },
    {
      "date": "2026-03-19",
      "value": 656.3121948242188
    },
    {
      "date": "2026-03-20",
      "value": 646.9034423828125
    },
    {
      "date": "2026-03-23",
      "value": 653.6959228515625
    },
    {
      "date": "2026-03-24",
      "value": 651.5015869140625
    },
    {
      "date": "2026-03-25",
      "value": 655.1322021484375
    },
    {
      "date": "2026-03-26",
      "value": 643.432373046875
    },
    {
      "date": "2026-03-27",
      "value": 632.4606323242188
    },
    {
      "date": "2026-03-30",
      "value": 630.3460693359375
    },
    {
      "date": "2026-03-31",
      "value": 648.6688842773438
    },
    {
      "date": "2026-04-01",
      "value": 653.5562744140625
    },
    {
      "date": "2026-04-02",
      "value": 654.144775390625
    },
    {
      "date": "2026-04-06",
      "value": 657.23681640625
    },
    {
      "date": "2026-04-07",
      "value": 657.5260009765625
    },
    {
      "date": "2026-04-08",
      "value": 674.27294921875
    },
    {
      "date": "2026-04-09",
      "value": 678.162841796875
    },
    {
      "date": "2026-04-10",
      "value": 677.7140502929688
    },
    {
      "date": "2026-04-13",
      "value": 684.3369750976562
    },
    {
      "date": "2026-04-14",
      "value": 692.675537109375
    },
    {
      "date": "2026-04-15",
      "value": 698.1414184570312
    },
    {
      "date": "2026-04-16",
      "value": 699.8569946289062
    },
    {
      "date": "2026-04-17",
      "value": 708.3152465820312
    },
    {
      "date": "2026-04-20",
      "value": 706.8988037109375
    },
    {
      "date": "2026-04-21",
      "value": 702.2708129882812
    },
    {
      "date": "2026-04-22",
      "value": 709.3825073242188
    },
    {
      "date": "2026-04-23",
      "value": 706.6295776367188
    },
    {
      "date": "2026-04-24",
      "value": 712.10546875
    },
    {
      "date": "2026-04-27",
      "value": 713.332275390625
    },
    {
      "date": "2026-04-28",
      "value": 709.8612060546875
    },
    {
      "date": "2026-04-29",
      "value": 709.7515258789062
    },
    {
      "date": "2026-04-30",
      "value": 716.8132934570312
    },
    {
      "date": "2026-05-01",
      "value": 718.7982177734375
    },
    {
      "date": "2026-05-04",
      "value": 716.1649780273438
    },
    {
      "date": "2026-05-05",
      "value": 721.9102172851562
    },
    {
      "date": "2026-05-06",
      "value": 731.9443359375
    },
    {
      "date": "2026-05-07",
      "value": 729.7001342773438
    },
    {
      "date": "2026-05-08",
      "value": 735.724609375
    },
    {
      "date": "2026-05-11",
      "value": 737.4002685546875
    },
    {
      "date": "2026-05-12",
      "value": 736.2831420898438
    },
    {
      "date": "2026-05-13",
      "value": 740.4025268554688
    },
    {
      "date": "2026-05-14",
      "value": 746.2474975585938
    },
    {
      "date": "2026-05-15",
      "value": 737.2706298828125
    },
    {
      "date": "2026-05-18",
      "value": 736.751953125
    },
    {
      "date": "2026-05-19",
      "value": 731.8446044921875
    },
    {
      "date": "2026-05-20",
      "value": 739.3452758789062
    },
    {
      "date": "2026-05-21",
      "value": 740.8114624023438
    },
    {
      "date": "2026-05-22",
      "value": 743.7239990234375
    },
    {
      "date": "2026-05-26",
      "value": 748.6613159179688
    },
    {
      "date": "2026-05-27",
      "value": 748.5316162109375
    },
    {
      "date": "2026-05-28",
      "value": 752.6609497070312
    },
    {
      "date": "2026-05-29",
      "value": 754.5361328125
    },
    {
      "date": "2026-06-01",
      "value": 756.5908203125
    },
    {
      "date": "2026-06-02",
      "value": 757.6182250976562
    },
    {
      "date": "2026-06-03",
      "value": 752.3018798828125
    },
    {
      "date": "2026-06-04",
      "value": 755.1445922851562
    },
    {
      "date": "2026-06-05",
      "value": 735.65478515625
    },
    {
      "date": "2026-06-08",
      "value": 737.3204345703125
    },
    {
      "date": "2026-06-09",
      "value": 735.1560668945312
    },
    {
      "date": "2026-06-10",
      "value": 723.56591796875
    },
    {
      "date": "2026-06-11",
      "value": 735.8642578125
    },
    {
      "date": "2026-06-12",
      "value": 739.843994140625
    },
    {
      "date": "2026-06-15",
      "value": 752.890380859375
    },
    {
      "date": "2026-06-16",
      "value": 748.4019775390625
    },
    {
      "date": "2026-06-17",
      "value": 739.0560302734375
    },
    {
      "date": "2026-06-18",
      "value": 746.739990234375
    },
    {
      "date": "2026-06-22",
      "value": 744.3900146484375
    },
    {
      "date": "2026-06-23",
      "value": 733.5800170898438
    },
    {
      "date": "2026-06-24",
      "value": 733.239990234375
    },
    {
      "date": "2026-06-25",
      "value": 734.2999877929688
    },
    {
      "date": "2026-06-26",
      "value": 728.989990234375
    },
    {
      "date": "2026-06-29",
      "value": 741.0
    },
    {
      "date": "2026-06-30",
      "value": 746.77001953125
    },
    {
      "date": "2026-07-01",
      "value": 745.760009765625
    },
    {
      "date": "2026-07-02",
      "value": 744.780029296875
    },
    {
      "date": "2026-07-06",
      "value": 751.280029296875
    },
    {
      "date": "2026-07-07",
      "value": 747.7100219726562
    },
    {
      "date": "2026-07-08",
      "value": 745.4000244140625
    },
    {
      "date": "2026-07-09",
      "value": 751.7100219726562
    },
    {
      "date": "2026-07-10",
      "value": 754.9500122070312
    },
    {
      "date": "2026-07-13",
      "value": 749.1699829101562
    },
    {
      "date": "2026-07-14",
      "value": 751.8300170898438
    },
    {
      "date": "2026-07-15",
      "value": 754.8099975585938
    },
    {
      "date": "2026-07-16",
      "value": 750.719970703125
    },
    {
      "date": "2026-07-17",
      "value": 743.2899780273438
    },
    {
      "date": "2026-07-20",
      "value": 742.0900268554688
    },
    {
      "date": "2026-07-21",
      "value": 748.280029296875
    }
  ],
  "execution_results": [
    {
      "message": "sandbox only; no brokerage order was placed",
      "side": "cash",
      "status": "simulated",
      "target_weight_delta": 0.2980999999999999,
      "ticker": "CASH",
      "timestamp": "2026-07-21T22:48:39"
    },
    {
      "message": "sandbox only; no brokerage order was placed",
      "side": "sell",
      "status": "simulated",
      "target_weight_delta": -0.06545454545454543,
      "ticker": "AAPL",
      "timestamp": "2026-07-21T22:48:39"
    },
    {
      "message": "sandbox only; no brokerage order was placed",
      "side": "sell",
      "status": "simulated",
      "target_weight_delta": -0.05454545454545453,
      "ticker": "MSFT",
      "timestamp": "2026-07-21T22:48:39"
    },
    {
      "message": "sandbox only; no brokerage order was placed",
      "side": "sell",
      "status": "simulated",
      "target_weight_delta": -0.05,
      "ticker": "AVGO",
      "timestamp": "2026-07-21T22:48:39"
    },
    {
      "message": "sandbox only; no brokerage order was placed",
      "side": "sell",
      "status": "simulated",
      "target_weight_delta": -0.04999999999999999,
      "ticker": "NVDA",
      "timestamp": "2026-07-21T22:48:39"
    },
    {
      "message": "sandbox only; no brokerage order was placed",
      "side": "sell",
      "status": "simulated",
      "target_weight_delta": -0.035,
      "ticker": "UNH",
      "timestamp": "2026-07-21T22:48:39"
    },
    {
      "message": "sandbox only; no brokerage order was placed",
      "side": "sell",
      "status": "simulated",
      "target_weight_delta": -0.023100000000000002,
      "ticker": "COST",
      "timestamp": "2026-07-21T22:48:39"
    },
    {
      "message": "sandbox only; no brokerage order was placed",
      "side": "sell",
      "status": "simulated",
      "target_weight_delta": -0.02,
      "ticker": "XOM",
      "timestamp": "2026-07-21T22:48:39"
    }
  ],
  "lookback_days": 900,
  "market_regime": {
    "benchmark": "SPY",
    "drawdown": -0.012325727512135232,
    "momentum": 0.08761043599713392,
    "price": 748.280029296875,
    "realized_vol": 0.11466331714189605,
    "trend_ma": 694.2735638427735,
    "trend_state": "bullish",
    "z": 0.7073839325360972
  },
  "mode": "real",
  "positions": {
    "AAPL": 0.18,
    "AVGO": 0.1,
    "COST": 0.07,
    "JNJ": 0.08,
    "JPM": 0.08,
    "MSFT": 0.15,
    "NVDA": 0.12,
    "UNH": 0.07,
    "V": 0.07,
    "XOM": 0.08
  },
  "price_as_of": "2026-07-21",
  "recommended_distribution": [
    {
      "action": "raise_cash",
      "current_weight": 0.0,
      "delta_weight": 0.2980999999999999,
      "priority": 0.3480999999999999,
      "reason": "raise or maintain cash buffer",
      "recommended_weight": 0.2980999999999999,
      "rule_ids": [
        "CASH_BUFFER"
      ],
      "sector": "Cash",
      "target_weight": 0.0,
      "ticker": "CASH"
    },
    {
      "action": "trim",
      "current_weight": 0.18,
      "delta_weight": -0.06545454545454543,
      "priority": 0.11545454545454543,
      "reason": "exceeds max single-name cap; over target weight; sector exceeds max cap",
      "recommended_weight": 0.11454545454545456,
      "rule_ids": [
        "OVER_TARGET",
        "SECTOR_CAP",
        "SINGLE_CAP"
      ],
      "sector": "Technology",
      "target_weight": 0.12,
      "ticker": "AAPL"
    },
    {
      "action": "trim",
      "current_weight": 0.15,
      "delta_weight": -0.054545454545454536,
      "priority": 0.10454545454545454,
      "reason": "over target weight; sector exceeds max cap; trailing-stop triggered",
      "recommended_weight": 0.09545454545454546,
      "rule_ids": [
        "OVER_TARGET",
        "SECTOR_CAP",
        "TRAILING_STOP"
      ],
      "sector": "Technology",
      "target_weight": 0.12,
      "ticker": "MSFT"
    },
    {
      "action": "trim",
      "current_weight": 0.1,
      "delta_weight": -0.05,
      "priority": 0.1,
      "reason": "sector exceeds max cap; stop-loss triggered; trailing-stop triggered",
      "recommended_weight": 0.05,
      "rule_ids": [
        "SECTOR_CAP",
        "STOP_LOSS",
        "TRAILING_STOP"
      ],
      "sector": "Technology",
      "target_weight": 0.12,
      "ticker": "AVGO"
    },
    {
      "action": "trim",
      "current_weight": 0.12,
      "delta_weight": -0.04999999999999999,
      "priority": 0.09999999999999999,
      "reason": "over target weight; sector exceeds max cap",
      "recommended_weight": 0.07,
      "rule_ids": [
        "OVER_TARGET",
        "SECTOR_CAP"
      ],
      "sector": "Technology",
      "target_weight": 0.07,
      "ticker": "NVDA"
    },
    {
      "action": "trim",
      "current_weight": 0.07,
      "delta_weight": -0.035,
      "priority": 0.085,
      "reason": "stop-loss triggered",
      "recommended_weight": 0.035,
      "rule_ids": [
        "STOP_LOSS"
      ],
      "sector": "Healthcare",
      "target_weight": 0.1,
      "ticker": "UNH"
    },
    {
      "action": "trim",
      "current_weight": 0.07,
      "delta_weight": -0.023100000000000002,
      "priority": 0.0731,
      "reason": "trailing-stop triggered",
      "recommended_weight": 0.046900000000000004,
      "rule_ids": [
        "TRAILING_STOP"
      ],
      "sector": "ConsumerStaples",
      "target_weight": 0.08,
      "ticker": "COST"
    },
    {
      "action": "trim",
      "current_weight": 0.08,
      "delta_weight": -0.020000000000000004,
      "priority": 0.07,
      "reason": "sector hyped (z=0.99)",
      "recommended_weight": 0.06,
      "rule_ids": [
        "SECTOR_HYPED"
      ],
      "sector": "Energy",
      "target_weight": 0.1,
      "ticker": "XOM"
    },
    {
      "action": "hold",
      "current_weight": 0.08,
      "delta_weight": 0.0,
      "priority": 0.0,
      "reason": "\u5f53\u524d\u6ca1\u6709\u89c4\u5219\u89e6\u53d1\u660e\u663e\u8c03\u6574\u3002",
      "recommended_weight": 0.08,
      "rule_ids": [],
      "sector": "Healthcare",
      "target_weight": 0.09,
      "ticker": "JNJ"
    },
    {
      "action": "hold",
      "current_weight": 0.08,
      "delta_weight": 0.0,
      "priority": 0.0,
      "reason": "\u5f53\u524d\u6ca1\u6709\u89c4\u5219\u89e6\u53d1\u660e\u663e\u8c03\u6574\u3002",
      "recommended_weight": 0.08,
      "rule_ids": [],
      "sector": "Financials",
      "target_weight": 0.1,
      "ticker": "JPM"
    },
    {
      "action": "hold",
      "current_weight": 0.07,
      "delta_weight": 0.0,
      "priority": 0.0,
      "reason": "\u5f53\u524d\u6ca1\u6709\u89c4\u5219\u89e6\u53d1\u660e\u663e\u8c03\u6574\u3002",
      "recommended_weight": 0.07,
      "rule_ids": [],
      "sector": "Financials",
      "target_weight": 0.1,
      "ticker": "V"
    }
  ],
  "risk_predictions": [
    {
      "features": {
        "drawdown_252": -0.01797806728461393,
        "ma_gap": 0.19347915818042094,
        "ret_126": 0.28497205982665763,
        "ret_21": 0.09976168415326603,
        "ret_252": 0.5581031342084697,
        "ret_63": 0.20139889335194527,
        "vol_21": 0.35757694534841705,
        "vol_63": 0.2817948928868371,
        "z_60": 1.7728501453075431
      },
      "model_version": "logistic_price_risk_v1",
      "risk_level": "low",
      "risk_probability": 0.12502899846483764,
      "ticker": "AAPL"
    },
    {
      "features": {
        "drawdown_252": -0.26159162288952476,
        "ma_gap": -0.08919691643475247,
        "ret_126": -0.1312109865667539,
        "ret_21": 0.0483658576666246,
        "ret_252": -0.21394555909195878,
        "ret_63": -0.04654370527657825,
        "vol_21": 0.3518501318574423,
        "vol_63": 0.3391010839518373,
        "z_60": -0.2695976065626987
      },
      "model_version": "logistic_price_risk_v1",
      "risk_level": "low",
      "risk_probability": 0.10104435913117342,
      "ticker": "MSFT"
    },
    {
      "features": {
        "drawdown_252": -0.11965903187978433,
        "ma_gap": 0.07747598885837448,
        "ret_126": 0.11444358735973337,
        "ret_21": -0.016137496396958828,
        "ret_252": 0.20390971915803502,
        "ret_63": 0.027079061069096966,
        "vol_21": 0.3630899026002514,
        "vol_63": 0.41264643412149393,
        "z_60": -0.18242550610741823
      },
      "model_version": "logistic_price_risk_v1",
      "risk_level": "low",
      "risk_probability": 0.11093066130985307,
      "ticker": "NVDA"
    },
    {
      "features": {
        "drawdown_252": -0.004842733441084546,
        "ma_gap": 0.1233735260019655,
        "ret_126": 0.11549907614465282,
        "ret_21": 0.066309731270082,
        "ret_252": 0.2079326466187701,
        "ret_63": 0.09399427206206257,
        "vol_21": 0.20445960463732615,
        "vol_63": 0.22242914984727913,
        "z_60": 1.787415297754606
      },
      "model_version": "logistic_price_risk_v1",
      "risk_level": "low",
      "risk_probability": 0.08114067500550001,
      "ticker": "JPM"
    },
    {
      "features": {
        "drawdown_252": -0.10923346967459613,
        "ma_gap": 0.11370028384091513,
        "ret_126": 0.18375399551785265,
        "ret_21": 0.1008635759489327,
        "ret_252": 0.45259293630601727,
        "ret_63": 0.03426155560319888,
        "vol_21": 0.24335581678381885,
        "vol_63": 0.2847964775172016,
        "z_60": 0.7654781157364935
      },
      "model_version": "logistic_price_risk_v1",
      "risk_level": "low",
      "risk_probability": 0.10995806083075524,
      "ticker": "XOM"
    },
    {
      "features": {
        "drawdown_252": -0.06222867172476165,
        "ma_gap": 0.1299455139186818,
        "ret_126": 0.15883661784902992,
        "ret_21": 0.09728972932301794,
        "ret_252": 0.5691616314221044,
        "ret_63": 0.09259728380360621,
        "vol_21": 0.30659835064703633,
        "vol_63": 0.24433961058994771,
        "z_60": 1.0250460373331642
      },
      "model_version": "logistic_price_risk_v1",
      "risk_level": "low",
      "risk_probability": 0.10917049409815141,
      "ticker": "JNJ"
    },
    {
      "features": {
        "drawdown_252": -0.025524475407583624,
        "ma_gap": 0.08204526802632728,
        "ret_126": 0.08831232254676524,
        "ret_21": 0.0873365662594423,
        "ret_252": 0.027447573738323294,
        "ret_63": 0.1357509285105336,
        "vol_21": 0.2323913132834223,
        "vol_63": 0.26091832401688214,
        "z_60": 1.6212363422717442
      },
      "model_version": "logistic_price_risk_v1",
      "risk_level": "low",
      "risk_probability": 0.07861997995370594,
      "ticker": "V"
    },
    {
      "features": {
        "drawdown_252": -0.15086993172865615,
        "ma_gap": -0.027206131750355578,
        "ret_126": -0.032970190752278916,
        "ret_21": -0.02336438196300017,
        "ret_252": -0.01735031176033852,
        "ret_63": -0.06741734708335223,
        "vol_21": 0.24062809540706967,
        "vol_63": 0.2271772381444116,
        "z_60": -1.2077918683386846
      },
      "model_version": "logistic_price_risk_v1",
      "risk_level": "low",
      "risk_probability": 0.0597569036713145,
      "ticker": "COST"
    },
    {
      "features": {
        "drawdown_252": 0.0,
        "ma_gap": 0.2881724413042901,
        "ret_126": 0.33603371611622923,
        "ret_21": 0.08826320681025468,
        "ret_252": 0.5851274265420365,
        "ret_63": 0.35662843655217547,
        "vol_21": 0.2666522295374335,
        "vol_63": 0.28365992555861363,
        "z_60": 1.7221978407625
      },
      "model_version": "logistic_price_risk_v1",
      "risk_level": "low",
      "risk_probability": 0.11349648869067104,
      "ticker": "UNH"
    },
    {
      "features": {
        "drawdown_252": -0.19614658088646686,
        "ma_gap": 0.06471884521041171,
        "ret_126": 0.10296480698730726,
        "ret_21": -0.0589238166246564,
        "ret_252": 0.3740802816375739,
        "ret_63": -0.03132469042707409,
        "vol_21": 0.44138387590989564,
        "vol_63": 0.5337955289411987,
        "z_60": -0.6522207267655825
      },
      "model_version": "logistic_price_risk_v1",
      "risk_level": "low",
      "risk_probability": 0.16720079944618452,
      "ticker": "AVGO"
    }
  ],
  "sector_weights": {
    "ConsumerStaples": 0.07,
    "Energy": 0.08,
    "Financials": 0.15000000000000002,
    "Healthcare": 0.15000000000000002,
    "Technology": 0.5499999999999999
  },
  "signals": [
    {
      "etf": "XLY",
      "ma": 116.91269092559814,
      "momentum": -0.056990117970802445,
      "pct_from_ma": -0.01747191141392901,
      "price": 114.87000274658203,
      "realized_vol": 0.17770123232446008,
      "sector": "ConsumerDiscretionary",
      "status": "cool",
      "std": 1.8439344851156285,
      "trend_ma": 116.91269092559814,
      "trend_state": "bearish",
      "z": -1.206535072015241
    },
    {
      "etf": "XLB",
      "ma": 48.32911836624145,
      "momentum": 0.03761223820828752,
      "pct_from_ma": 0.03664209420208708,
      "price": 50.099998474121094,
      "realized_vol": 0.16692616703263422,
      "sector": "Materials",
      "status": "cool",
      "std": 0.770883983629981,
      "trend_ma": 48.32911836624145,
      "trend_state": "bullish",
      "z": -1.171757342980038
    },
    {
      "etf": "XLC",
      "ma": 114.05993480682373,
      "momentum": -0.039087652935846595,
      "pct_from_ma": -0.03533174058316013,
      "price": 110.02999877929688,
      "realized_vol": 0.18013291632324996,
      "sector": "CommunicationServices",
      "status": "neutral",
      "std": 3.231425013755682,
      "trend_ma": 114.05993480682373,
      "trend_state": "bearish",
      "z": -0.8169112807991649
    },
    {
      "etf": "XLU",
      "ma": 44.32199874877929,
      "momentum": 0.049156309794875064,
      "pct_from_ma": 0.013492158229495121,
      "price": 44.91999816894531,
      "realized_vol": 0.14413943843206822,
      "sector": "Utilities",
      "status": "neutral",
      "std": 0.8537363507664457,
      "trend_ma": 44.32199874877929,
      "trend_state": "bullish",
      "z": 0.048549417355336716
    },
    {
      "etf": "XLK",
      "ma": 153.81038166046142,
      "momentum": 0.24447611061549557,
      "pct_from_ma": 0.17534328195330318,
      "price": 180.77999877929688,
      "realized_vol": 0.3211690805767666,
      "sector": "Technology",
      "status": "neutral",
      "std": 9.572820237919,
      "trend_ma": 153.81038166046142,
      "trend_state": "bullish",
      "z": 0.11991277532151287
    },
    {
      "etf": "XLP",
      "ma": 81.12377296447754,
      "momentum": 0.03665437029330176,
      "pct_from_ma": 0.03619437911747436,
      "price": 84.05999755859375,
      "realized_vol": 0.188281092136995,
      "sector": "ConsumerStaples",
      "status": "neutral",
      "std": 1.081978624568482,
      "trend_ma": 81.12377296447754,
      "trend_state": "bullish",
      "z": 0.3293032545631445
    },
    {
      "etf": "XLI",
      "ma": 165.44067207336425,
      "momentum": 0.07611037687467714,
      "pct_from_ma": 0.07990375899151947,
      "price": 178.66000366210938,
      "realized_vol": 0.16819369552597005,
      "sector": "Industrials",
      "status": "neutral",
      "std": 4.595960125474785,
      "trend_ma": 165.44067207336425,
      "trend_state": "bullish",
      "z": 0.5395522198135231
    },
    {
      "etf": "XLE",
      "ma": 51.39813325881958,
      "momentum": 0.24359126251879015,
      "pct_from_ma": 0.13817363182079756,
      "price": 58.5,
      "realized_vol": 0.19073074697308023,
      "sector": "Energy",
      "status": "hyped",
      "std": 1.952141270261032,
      "trend_ma": 51.39813325881958,
      "trend_state": "bullish",
      "z": 0.9885875699694832
    },
    {
      "etf": "XLV",
      "ma": 150.51818359375,
      "momentum": 0.037745165415911996,
      "pct_from_ma": 0.06465542018840909,
      "price": 160.25,
      "realized_vol": 0.21212294762037753,
      "sector": "Healthcare",
      "status": "warm",
      "std": 6.709546075051455,
      "trend_ma": 150.51818359375,
      "trend_state": "bullish",
      "z": 1.2939996493709316
    },
    {
      "etf": "XLF",
      "ma": 52.330224704742434,
      "momentum": 0.03960307516524808,
      "pct_from_ma": 0.07222930776497472,
      "price": 56.11000061035156,
      "realized_vol": 0.1323315997877026,
      "sector": "Financials",
      "status": "warm",
      "std": 1.877278489765126,
      "trend_ma": 52.330224704742434,
      "trend_state": "bullish",
      "z": 1.6829431304725728
    },
    {
      "etf": "XLRE",
      "ma": 41.890371265411375,
      "momentum": 0.08748048779413309,
      "pct_from_ma": 0.07900692683191424,
      "price": 45.20000076293945,
      "realized_vol": 0.15983819646940295,
      "sector": "RealEstate",
      "status": "hyped",
      "std": 0.6147333355261734,
      "trend_ma": 41.890371265411375,
      "trend_state": "bullish",
      "z": 1.7014566403633007
    }
  ],
  "snapshot": {
    "config_name": "config.yaml",
    "generated_at": "2026-07-21T22:48:39.335081+00:00",
    "is_example_config": false,
    "lookback_days": 900,
    "mode": "real"
  },
  "suggestions": [
    {
      "action": "hold",
      "delta_weight": 0.2980999999999999,
      "metadata": {},
      "reason": "raise or maintain cash buffer",
      "rule_ids": [
        "CASH_BUFFER"
      ],
      "ticker": "CASH"
    },
    {
      "action": "trim",
      "delta_weight": -0.06545454545454543,
      "metadata": {},
      "reason": "exceeds max single-name cap; over target weight; sector exceeds max cap",
      "rule_ids": [
        "OVER_TARGET",
        "SECTOR_CAP",
        "SINGLE_CAP"
      ],
      "ticker": "AAPL"
    },
    {
      "action": "trim",
      "delta_weight": -0.05454545454545453,
      "metadata": {},
      "reason": "over target weight; sector exceeds max cap; trailing-stop triggered",
      "rule_ids": [
        "OVER_TARGET",
        "SECTOR_CAP",
        "TRAILING_STOP"
      ],
      "ticker": "MSFT"
    },
    {
      "action": "trim",
      "delta_weight": -0.05,
      "metadata": {},
      "reason": "sector exceeds max cap; stop-loss triggered; trailing-stop triggered",
      "rule_ids": [
        "SECTOR_CAP",
        "STOP_LOSS",
        "TRAILING_STOP"
      ],
      "ticker": "AVGO"
    },
    {
      "action": "trim",
      "delta_weight": -0.04999999999999999,
      "metadata": {},
      "reason": "over target weight; sector exceeds max cap",
      "rule_ids": [
        "OVER_TARGET",
        "SECTOR_CAP"
      ],
      "ticker": "NVDA"
    },
    {
      "action": "trim",
      "delta_weight": -0.035,
      "metadata": {},
      "reason": "stop-loss triggered",
      "rule_ids": [
        "STOP_LOSS"
      ],
      "ticker": "UNH"
    },
    {
      "action": "trim",
      "delta_weight": -0.023100000000000002,
      "metadata": {},
      "reason": "trailing-stop triggered",
      "rule_ids": [
        "TRAILING_STOP"
      ],
      "ticker": "COST"
    },
    {
      "action": "trim",
      "delta_weight": -0.02,
      "metadata": {},
      "reason": "sector hyped (z=0.99)",
      "rule_ids": [
        "SECTOR_HYPED"
      ],
      "ticker": "XOM"
    }
  ],
  "target_weights": {
    "AAPL": 0.12,
    "AVGO": 0.12,
    "COST": 0.08,
    "JNJ": 0.09,
    "JPM": 0.1,
    "MSFT": 0.12,
    "NVDA": 0.07,
    "UNH": 0.1,
    "V": 0.1,
    "XOM": 0.1
  },
  "universe": {
    "benchmark": "SPY",
    "sector_etfs": {
      "CommunicationServices": "XLC",
      "ConsumerDiscretionary": "XLY",
      "ConsumerStaples": "XLP",
      "Energy": "XLE",
      "Financials": "XLF",
      "Healthcare": "XLV",
      "Industrials": "XLI",
      "Materials": "XLB",
      "RealEstate": "XLRE",
      "Technology": "XLK",
      "Utilities": "XLU"
    },
    "tickers": [
      "AAPL",
      "AVGO",
      "COST",
      "JNJ",
      "JPM",
      "MSFT",
      "NVDA",
      "UNH",
      "V",
      "XOM"
    ]
  }
}
